basicprogressbar/__init__.py
basicprogressbar/basicprogressbar.py
basicprogressbar/discordprogressbar.py
basicprogressbar/discordprogressbarasync.py
basicprogressbar-1.1.3.dist-info/licenses/LICENSE
basicprogressbar-1.1.3.dist-info/METADATA
basicprogressbar-1.1.3.dist-info/WHEEL
basicprogressbar-1.1.3.dist-info/top_level.txt
basicprogressbar-1.1.3.dist-info/RECORD
