Metadata-Version: 2.4
Name: basicprogressbar
Version: 1.1.3
Summary: Basic progress bar and discord progress bar
Author-email: Sumiza <sumiza@gmail.com>
License-Expression: MIT
Project-URL: Homepage, https://github.com/Sumiza/basicprogressbar/
Project-URL: Bug Tracker, https://github.com/Sumiza/basicprogressbar/issues
Classifier: Programming Language :: Python :: 3.10
Classifier: Programming Language :: Python :: 3.11
Classifier: Programming Language :: Python :: 3.12
Classifier: Programming Language :: Python :: 3.13
Classifier: Programming Language :: Python :: 3.14
Classifier: Operating System :: OS Independent
Requires-Python: >=3.10
License-File: LICENSE
Provides-Extra: timer
Requires-Dist: secondstotext; extra == "timer"
Provides-Extra: discord
Requires-Dist: requests; extra == "discord"
Provides-Extra: async
Requires-Dist: httpx; extra == "async"
Provides-Extra: all
Requires-Dist: secondstotext; extra == "all"
Requires-Dist: requests; extra == "all"
Requires-Dist: httpx; extra == "all"
Dynamic: license-file
